Lab 1/p1.v
module p1(A,B,C,D,f);
input A,B,C,D;
output f;
and(k1,A,B);
or(k2,k1,C);
not(k3,k2);
and(k4,k3,D);
and(k5,A,B);
or(k6,k5,C);
or(k7,k6,D);
and(f,k4,k7);
endmodule

Lab 1/p1_tb.v
`timescale 1ns/1ns
`include "p1.v"

module p1_tb();

reg A,B,C,D;
wire f;

p1 uut(A,B,C,D,f);
initial begin 

	$dumpfile("p1_tb.vcd");
	$dumpvars(0,p1_tb); 
	
	A=0;
	B=0; 
	C=0;
	D=0;
	#20;
	
	A=0;
	B=0;
	C=0;
	D=1;
	#20;
	
	A=0;
	B=0;
	C=1;
	D=0;
	#20;
	
	A=0;
	B=0;
	C=1;
	D=1;
	#20;
	
	A=0;
	B=1;
	C=0;
	D=0;
	#20;
	
	A=0;
	B=1;
	C=0;
	D=1;
	#20;
	
	A=0;
	B=1;
	C=1;
	D=0;
	#20;
	
	A=0;
	B=1;
	C=1;
	D=1;
	#20;
	
	A=1;
	B=0;
	C=0;
	D=0;
	#20;
	
	A=1;
	B=0;
	C=0;
	D=1;
	#20;
	
	A=1;
	B=0;
	C=1;
	D=0;
	#20;
	
	A=1;
	B=0;
	C=1;
	D=1;
	#20;
	
	A=1;
	B=1;
	C=0;
	D=0;
	#20;
	
	A=1;
	B=1;
	C=0;
	D=1;
	#20;
	
	A=1;
	B=1;
	C=1;
	D=0;
	#20;

	A=1;
	B=1; 
	C=1;
	D=1;
	#20;
	
	$display("Test complete");
end
endmodule

Lab 1/p1_tb.vcd
$date
	Mon Sep  5 09:38:19 2022
$end
$version
	Icarus Verilog
$end
$timescale
	1ns
$end
$scope module p1_tb $end
$var wire 1 ! f $end
$var reg 1 " A $end
$var reg 1 # B $end
$var reg 1 $ C $end
$var reg 1 % D $end
$scope module uut $end
$var wire 1 " A $end
$var wire 1 # B $end
$var wire 1 $ C $end
$var wire 1 % D $end
$var wire 1 ! f $end
$var wire 1 & k1 $end
$var wire 1 ' k2 $end
$var wire 1 ( k3 $end
$var wire 1 ) k4 $end
$var wire 1 * k5 $end
$var wire 1 + k6 $end
$var wire 1 , k7 $end
$upscope $end
$upscope $end
$enddefinitions $end
#0
$dumpvars
0,
0+
0*
0)
1(
0'
0&
0%
0$
0#
0"
0!
$end
#20
1!
1)
1,
1%
#40
0!
0(
0)
1'
1+
0%
1$
#60
1%
#80
1(
0,
0'
0+
0%
0$
1#
#100
1!
1)
1,
1%
#120
0!
0(
0)
1'
1+
0%
1$
#140
1%
#160
1(
0,
0'
0+
0%
0$
0#
1"
#180
1!
1)
1,
1%
#200
0!
0(
0)
1'
1+
0%
1$
#220
1%
#240
1&
1*
0%
0$
1#
#260
1%
#280
0%
1$
#300
1%
