Lab 3/P1.v
module P1(A,B,C,D,f);
input A,B,C,D;
output f;
assign f=~(~(~A&~C)&~(B&~C)&~(~A&D)&~(B&D));
endmodule

Lab 3/P1_tb.v
`timescale 1ns/1ns
`include "P1.v"

module P1_tb();

reg A,B,C,D;
wire f;

P1 uut(A,B,C,D,f);
initial begin 

	$dumpfile("P1_tb.vcd");
	$dumpvars(0, P1_tb); 
	
	A=0;
	B=0; 
	C=0;
	D=0;
	#20;
	
	A=0;
	B=0;
	C=0;
	D=1;
	#20;
	
	A=0;
	B=0;
	C=1;
	D=0;
	#20;
	
	A=0;
	B=0;
	C=1;
	D=1;
	#20;
	
	A=0;
	B=1;
	C=0;
	D=0;
	#20;
	
	A=0;
	B=1;
	C=0;
	D=1;
	#20;
	
	A=0;
	B=1;
	C=1;
	D=0;
	#20;
	
	A=0;
	B=1;
	C=1;
	D=1;
	#20;
	
	A=1;
	B=0;
	C=0;
	D=0;
	#20;
	
	A=1;
	B=0;
	C=0;
	D=1;
	#20;
	
	A=1;
	B=0;
	C=1;
	D=0;
	#20;
	
	A=1;
	B=0;
	C=1;
	D=1;
	#20;
	
	A=1;
	B=1;
	C=0;
	D=0;
	#20;
	
	A=1;
	B=1;
	C=0;
	D=1;
	#20;
	
	A=1;
	B=1;
	C=1;
	D=0;
	#20;

	A=1;
	B=1; 
	C=1;
	D=1;
	#20;
	
	$display("Test complete");
end
endmodule

Lab 3/P1_tb.vcd
$date
	Mon Sep  5 10:56:00 2022
$end
$version
	Icarus Verilog
$end
$timescale
	1ns
$end
$scope module P1_tb $end
$var wire 1 ! f $end
$var reg 1 " A $end
$var reg 1 # B $end
$var reg 1 $ C $end
$var reg 1 % D $end
$scope module uut $end
$var wire 1 " A $end
$var wire 1 # B $end
$var wire 1 $ C $end
$var wire 1 % D $end
$var wire 1 ! f $end
$upscope $end
$upscope $end
$enddefinitions $end
#0
$dumpvars
0%
0$
0#
0"
1!
$end
#20
1%
#40
0!
0%
1$
#60
1!
1%
#80
1!
0%
0$
1#
#100
1%
#120
0!
0%
1$
#140
1!
1%
#160
0!
0%
0$
0#
1"
#180
1%
#200
0%
1$
#220
1%
#240
1!
0%
0$
1#
#260
1%
#280
0!
0%
1$
#300
1!
1%
