Lab 2/P1a.v
module P1a(A,B,C,D,f);
input A,B,C,D;
output f;
and(k1,C,D);
and(k2,~A,B);
or(k3,k1,k2);
and(k4,~C,~D,B);
and(k5,~B,C);
or(k6,k4,k5);
or(f,k3,k6);
endmodule

Lab 2/P1a_tb.v
`timescale 1ns/1ns
`include "P1a.v"

module P1a_tb();

reg A,B,C,D;
wire f;

P1a uut(A,B,C,D,f);
initial begin 

	$dumpfile("P1a_tb.vcd");
	$dumpvars(0,P1a_tb); 
	
	A=0;
	B=0; 
	C=0;
	D=0;
	#20;
	
	A=0;
	B=0;
	C=0;
	D=1;
	#20;
	
	A=0;
	B=0;
	C=1;
	D=0;
	#20;
	
	A=0;
	B=0;
	C=1;
	D=1;
	#20;
	
	A=0;
	B=1;
	C=0;
	D=0;
	#20;
	
	A=0;
	B=1;
	C=0;
	D=1;
	#20;
	
	A=0;
	B=1;
	C=1;
	D=0;
	#20;
	
	A=0;
	B=1;
	C=1;
	D=1;
	#20;
	
	A=1;
	B=0;
	C=0;
	D=0;
	#20;
	
	A=1;
	B=0;
	C=0;
	D=1;
	#20;
	
	A=1;
	B=0;
	C=1;
	D=0;
	#20;
	
	A=1;
	B=0;
	C=1;
	D=1;
	#20;
	
	A=1;
	B=1;
	C=0;
	D=0;
	#20;
	
	A=1;
	B=1;
	C=0;
	D=1;
	#20;
	
	A=1;
	B=1;
	C=1;
	D=0;
	#20;

	A=1;
	B=1; 
	C=1;
	D=1;
	#20;
	
	$display("Test complete");
end
endmodule

Lab 2/P1a_tb.vcd
$date
	Mon Sep  5 09:12:25 2022
$end
$version
	Icarus Verilog
$end
$timescale
	1ns
$end
$scope module P1a_tb $end
$var wire 1 ! f $end
$var reg 1 " A $end
$var reg 1 # B $end
$var reg 1 $ C $end
$var reg 1 % D $end
$scope module uut $end
$var wire 1 " A $end
$var wire 1 # B $end
$var wire 1 $ C $end
$var wire 1 % D $end
$var wire 1 ! f $end
$var wire 1 & k1 $end
$var wire 1 ' k2 $end
$var wire 1 ( k3 $end
$var wire 1 ) k4 $end
$var wire 1 * k5 $end
$var wire 1 + k6 $end
$upscope $end
$upscope $end
$enddefinitions $end
#0
$dumpvars
0+
0*
0)
0(
0'
0&
0%
0$
0#
0"
0!
$end
#20
1%
#40
1!
1+
1*
0%
1$
#60
1(
1&
1%
#80
1)
1+
0&
0*
1'
0%
0$
1#
#100
0+
0)
1%
#120
0%
1$
#140
1&
1%
#160
0!
0(
0&
0'
0%
0$
0#
1"
#180
1%
#200
1!
1+
1*
0%
1$
#220
1(
1&
1%
#240
1!
0(
1)
1+
0&
0*
0%
0$
1#
#260
0!
0+
0)
1%
#280
0%
1$
#300
1!
1(
1&
1%
