Lab 4/P1Fa.v
module P1Fa(A,B,Cin,Cout,S);
input A,B,Cin;
output S,Cout;
assign S=(A^B^Cin);
assign Cout=(A&B)|(A&Cin)|(B&Cin);
endmodule

Lab 4/P1Fa_tb.v
`timescale 1ns/1ns
`include "P1Fa.v"

module P1Fa_tb();

reg A,B,Cin;
wire S,Cout;

P1Fa uut(A,B,Cin,Cout,S);
initial begin 

	$dumpfile("P1Fa_tb.vcd");
	$dumpvars(0, P1Fa_tb); 
	
	A=0;
	B=0;
	Cin=0;
	#20
	
	A=0;
	B=0;
	Cin=1;
	#20
	
	A=0;
	B=1;
	Cin=0;
	#20
	
	A=0;
	B=1;
	Cin=1;
	#20
	
	A=1;
	B=0;
	Cin=0;
	#20
	
	A=1;
	B=0;
	Cin=1;
	#20
	
	A=1;
	B=1;
	Cin=0;
	#20
	
	A=1;
	B=1;
	Cin=1;
	#20
	
	$display("Test COmplete");
	
end
endmodule

Lab 4/P1Fa_tb.vcd
$date
	Mon Sep 12 09:27:42 2022
$end
$version
	Icarus Verilog
$end
$timescale
	1ns
$end
$scope module P1Fa_tb $end
$var wire 1 ! S $end
$var wire 1 " Cout $end
$var reg 1 # A $end
$var reg 1 $ B $end
$var reg 1 % Cin $end
$scope module uut $end
$var wire 1 # A $end
$var wire 1 $ B $end
$var wire 1 % Cin $end
$var wire 1 " Cout $end
$var wire 1 ! S $end
$upscope $end
$upscope $end
$enddefinitions $end
#0
$dumpvars
0%
0$
0#
0"
0!
$end
#20
1!
1%
#40
0%
1$
#60
1"
0!
1%
#80
0"
1!
0%
0$
1#
#100
1"
0!
1%
#120
0%
1$
#140
1!
1%
